[
    {
        "inputs": ["sock"],
        "outputs": ["3 toad for game bro lesgoooooooooooo", "local semi-limited furry"]
    },
    {
        "inputs": ["socks", "yummy"],
        "outputs": ["sock's ultimate clone"]
    },
    {
        "inputs": ["wip"],
        "outputs": ["King of Black People"]
    },
    {
        "inputs": ["khrey"],
        "outputs": ["darkwater bromken"]
    },
    {
        "inputs": ["f"],
        "outputs": ["https://media.discordapp.net/attachments/575461999639789626/852299185934958632/received_256610138868311_50.png"]
    }
]